obsscenetransporter/__init__.py
obsscenetransporter/__main__.py
obsscenetransporter/pathformatter.py
obsscenetransporter/pathhelper.py
obsscenetransporter/scenecollection.py
obs_scene_transporter-0.9.13.dist-info/LICENSE
obs_scene_transporter-0.9.13.dist-info/METADATA
obs_scene_transporter-0.9.13.dist-info/WHEEL
obs_scene_transporter-0.9.13.dist-info/entry_points.txt
obs_scene_transporter-0.9.13.dist-info/top_level.txt
obs_scene_transporter-0.9.13.dist-info/RECORD
