Metadata-Version: 2.1
Name: obs-scene-transporter
Version: 0.9.13
Summary: Import and export OBS Studio scenes including all assets
Home-page: https://github.com/stblassitude/obs-scene-transporter
Author: Stefan Bethke
Author-email: stb@lassitu.de
License: UNKNOWN
Project-URL: Bug Tracker, https://github.com/stblassitude/obs-scene-transporter/issues
Platform: UNKNOWN
Classifier: Programming Language :: Python :: 3
Classifier: License :: OSI Approved :: MIT License
Classifier: Operating System :: OS Independent
Requires-Python: >=3.6
